{"schema":{"fields":[{"name":"level_1","type":"string"},{"name":"level_1_text","type":"string"},{"name":"level_2","type":"string"},{"name":"level_2_content","type":"string"}],"pandas_version":"1.4.0"},"data":[{"level_1":"1 Introduction","level_1_text":"mnras 000, 1\u201313 (2018)\npreprint 3 january 2019\ncompiled using mnras l\na\nt\nex style \ufb01le v3.0\nthe asas-sn catalog of variable stars iii: variables in\nthe southern tess continuous viewing zone\nt. jayasinghe1,2\u22c6, k. z. stanek1,2, c. s. kochanek1,2, b. j. shappee3,\nt. w. -s. holoien4, todd a. thompson1,2,5, j. l. prieto6,7, subo dong8, m. pawlak9,\no. pejcha9, j. v. shields1, g. pojmanski10, s. otero11, n. hurst12, c. a. britt12,\nd. will1,12\n1department of astronomy, the ohio state university, 140 west 18th avenue, columbus, oh 43210, usa\n2center for cosmology and astroparticle physics, the ohio state university, 191 w. woodru\ufb00avenue, columbus, oh 43210, usa\n3institute for astronomy, university of hawaii, 2680 woodlawn drive, honolulu, hi 96822,usa\n4carnegie observatories, 813 santa barbara street, pasadena, ca 91101, usa\n5institute for advanced study, princeton, nj, 08540\n6n\u00b4\nucleo de astronom\u00b4\n\u0131a de la facultad de ingenier\u00b4\n\u0131a y ciencias, universidad diego portales, av. ej\u00b4\nercito 441, santiago, chile\n7millennium institute of astrophysics, santiago, chile\n8kavli institute for astronomy and astrophysics, peking university, yi he yuan road 5, hai dian district, china\n9institute of theoretical physics, faculty of mathematics and physics, charles university in prague, czech republic\n10warsaw university observatory, al ujazdowskie 4, 00-478 warsaw, poland\n11the american association of variable star observers, 49 bay state road, cambridge, ma 02138, usa\n12asc technology services, 433 mendenhall laboratory 125 south oval mall columbus oh, 43210, usa\naccepted xxx. received yyy; in original form zzz\nabstract\nthe all-sky automated survey for supernovae (asas-sn) provides long baseline (\u223c4\nyrs) light curves for sources brighter than v\u227217 mag across the whole sky. the tran-\nsiting exoplanet survey satellite (tess) has started to produce high-quality light\ncurves with a baseline of at least 27 days, eventually for most of the sky. the combi-\nnation of asas-sn and tess light curves probes both long and short term variability\nin great detail, especially towards the tess continuous viewing zones (cvz) at the\necliptic poles. we have produced \u223c1.3 million v-band light curves covering a total of\n\u223c1000 deg2 towards the southern tess cvz and have systematically searched these\nsources for variability. we have identi\ufb01ed \u223c11, 700 variables, including \u223c7, 000 new dis-\ncoveries. the light curves and characteristics of the variables are all available through\nthe asas-sn variable stars database (https:\/\/asas-sn.osu.edu\/variables). we\nalso introduce an online resource to obtain pre-computed asas-sn v-band light\ncurves (https:\/\/asas-sn.osu.edu\/photometry) starting with the light curves of the\n\u223c1.3 million sources studied in this work. this e\ufb00ort will be extended to provide asas-\nsn light curves for \u223c50 million sources over the entire sky.\nkey words: stars:variables \u2013 stars:binaries:eclipsing \u2013 catalogues \u2013surveys\n1\nintroduction\n","level_2":null,"level_2_content":null},{"level_1":"2 Observations and Data reduction","level_1_text":"we started with the aavso photometric all-sky survey\n(apass; henden et al. 2015) dr9 catalog as our input\nsource catalog. we selected all the apass sources with\nv < 17 mag in all the asas-sn \ufb01elds with central \ufb01eld\ncoordinates within 18 deg from the southern ecliptic pole\n(\u03b1 = 90 deg, \u03b4 = \u221266.55 deg). this resulted in a list of \u223c1.3m\nsources spanning a total of \u223c1, 000 deg2. asas-sn v-band\nobservations were made by the\u201cbrutus\u201d(haleakala, hawaii)\nand \u201ccassius\u201d (ctio, chile) quadruple telescopes between\n2013 and 2018. each asas-sn \ufb01eld has \u223c200-600 epochs\nof observation to a depth of v \u227217 mag. each camera has a\n\ufb01eld of view of 4.5 deg2, the pixel scale is 8.\n\u2032\u20320 and the fwhm\nis \u223c2 pixels. asas-sn nominally saturates at \u223c10\u221211 mag,\nbut light curves of saturated sources are sometimes quite\ngood due to corrections made for bleed trails (see kochanek\net al. 2017).\nthe light curves for these sources were extracted as de-\nscribed in jayasinghe et al. (2018a) using image subtraction\n(alard & lupton 1998; alard 2000) and aperture photome-\ntry on the subtracted images with a 2 pixel radius aperture.\nthe apass catalog was used for calibration. the zero point\no\ufb00sets between the di\ufb00erent cameras were corrected as de-\nscribed in jayasinghe et al. (2018a).\nfigure 1 illustrates the relationship between the mea-\nsured mean asas-sn v-band magnitudes and the apass\ndr9 v-band magnitudes. sources with vmean \u227214 mag\nhave similar v-band magnitudes, but a large fraction of the\nsources with vmean \u227314 mag show a discrepancy between the\nasas-sn and apass measurements. this is due to blend-\ning in \ufb01elds with signi\ufb01cant stellar densities (i.e., the lmc\nin this work). the relatively large asas-sn pixel scale of\n8.\n\u2032\u20320 as compared to the smaller apass pixel scale of 2.\n\u2032\u20326\nmakes asas-sn photometry more susceptible to blending.\nthus, asas-sn v-band measurements are systematically\nbrighter for most sources in the lmc due to blended light.\nthe light curve extraction provides a statistical error\nestimate, but the scatter in the light curves of apparently\nnon-variable sources is generally larger than expected given\nthe nominal statistical uncertainties. in jayasinghe et al.\n(2018a), we used the reduced \u03c72 statistic,\n\u03c72\nndof\n=\n1\nn \u22121\nn\n\u00f5\ni=1\n\u0012vi \u2212vmean\n\u03c3(vmean)\n\u00132\n\u22481,\n(1)\nwhere vi is the v-band magnitude for epoch i, and vmean\nmnras 000, 1\u201313 (2018)\nasas-sn catalog of variable stars iii\n3\n6\n8\n10\n12\n14\n16\n18\nasas-sn v-band magnitude\n5\n0\n5\nresidual\n6\n8\n10\n12\n14\n16\n18\n20\napass dr9 v-band magnitude\nfigure 1. comparison of the mean asas-sn v-band magni-\ntudes to the apass dr9 v-band magnitudes. the red dashed\nline illustrates a perfect calibration.\nis the mean v-band magnitude to determine the typical to-\ntal uncertainty \u03c3(vmean) as a function of magnitude. in this\nwork, we update our approach to estimating the systematic\nuncertainties in the asas-sn photometry.\nwe can view the photometric errors as the quadrature\nsum of the estimated statistical uncertainty \u03c3stat and a sys-\ntematic \u03c3sys , with\n\u03c32 = \u03c32\nsys + \u03c32\nstat .\n(2)\nwe can measure \u03c3 as the root-mean-square (rms) scatter in\nthe light curves of non-variable stars, and then subtract the\nestimated statistical errors to derive \u03c3sys, with the results\nshown in figure 2 for the 1.3m sources in our sample. for\nsources with vmean < 13 mag, the photometric uncertainties\napproach an asas-sn error \ufb02oor of \u223c0.02 mag. for the\nsources with vmean > 13 mag, we \ufb01t a third order polynomial,\nlog \u03c3sys = a(x \u221213)3 + b(x \u221213)2 + c(x \u221213) \u22121.738,\n(3)\nwith a = \u22121.03\u00d710\u22122, b = 8.6\u00d710\u22122, and c = 3.6\u00d710\u22122 to the\nmedian of the \u03c3sys versus vmean distribution. the polynomial\nsmoothly joins to 0.02 mag at v = 13 mag. to correct the\nerrors in the light curves, we replace the formal magnitude\nerrors by using equation 2 and either equation 3 or 0.02 mag\nfor \u03c3sys.\nwe also identi\ufb01ed a systematic issue that a\ufb00ects the\nlight curves of certain sources due to malfunctioning shut-\nters. the shutters in the asas-sn cameras periodically\nstart to fail. degraded shutters do not close completely, and\nstray light from neighboring bright sources can impart trails\non the images during readout (figure 3). this systematic\nis illustrated in the light curve for the non-variable source\nj072955.48-521556.8 (figure 3). we see that after the mal-\nfunctioning shutter is replaced, the light curve returns to\n10\n11\n12\n13\n14\n15\n16\n17\n18\nvmean\n2.0\n1.5\n1.0\n0.5\n0.0\nlog(\u03c3sys)\npolynomial fit (n=3)\nbinned median: \u03c3sys\n100\n101\n102\n103\nnumber of sources\nfigure 2. the distribution of \u03c3sys for the \u223c1.3m sources. the\nred points are the binned median values of \u03c3sys for this sample in\nbins of \u223c0.25 mag. the blue curve shows a third order polynomial\nmodel for sources with v > 13 mag (equation 3).\n6500\n7000\n7500\n8000\n8500\n14.94\n16.02\n j072955.48-521556.8\nhjd-2450000\nv magnitude\nfigure 3. top: examples of images that are a\ufb00ected by a\nmalfunctioning shutter for the non-variable source j072955.48-\n521556.8, with the reference image shown in the bottom right,\nbottom: the light curve for the source j072955.48-521556.8 with\nthe a\ufb00ected epochs highlighted by the red boxes.\nnormal, but after \u223c700 days, the shutter begins to fail again.\nsome fraction of our asas-sn light curves will be a\ufb00ected\nby this systematic.\n","level_2":null,"level_2_content":null},{"level_1":"3 Variability Analysis","level_1_text":null,"level_2":"3.1 Cross-matches to external catalogs","level_2_content":"here we describe the procedure we used to identify and char-\nacterize variables in the source list. we describe how we\nmnras 000, 1\u201313 (2018)\n4\nt. jayasinghe et al.\ncross-matched the apass sources to external catalogues in\nsection \u00a73.1. in section \u00a73.2, we describe the procedure we\ntook to identify candidate variable sources. in section \u00a73.3,\nwe discuss the application of the v2 random forest classi\ufb01er\nmodel from jayasinghe et al. (2018b) to classify these vari-\nables, and in section \u00a73.4, we discuss the corrections done to\nmitigate the e\ufb00ects of blending on the candidate variables.\n3.1\ncross-matches to external catalogs\n"},{"level_1":"3 Variability Analysis","level_1_text":null,"level_2":"3.4 Blending Corrections","level_2_content":"the large pixel scale of the asas-sn images (8.\n\u2032\u20320) and the\nfwhm (\u223c16.\n\u2032\u20320) results in blending towards crowded re-\ngions. the apass catalog was constructed with images that\nhave a signi\ufb01cantly smaller pixel scale (2.\n\u2032\u20326), and as a result\nof this, multiple apass sources can fall into a single asas-\nsn pixel. we do not correct for the contaminating light in\nthe photometry of the blended sources, but we identify and\ncorrect blended variable groups in our catalog.\nsince we extracted light curves for the positions of\napass sources, we can have two or more such sources inside\na single asas-sn resolution element. if we select the sources\nwith another apass neighbor within 30.\n\u2032\u20320, we \ufb01nd that 559\nof the \u223c12, 300 variables had a neighbor within 30.\n\u2032\u20320. we\ncompute the \ufb02ux variability amplitudes for these sources\nusing a random forest regression model (jayasinghe et al.\n2018b). the majority of the variable groups consisted of two\nsources, with a few groups consisting of up to three sources.\nfor each variable group, we consider the source with the\nlargest \ufb02ux variability as the \u2018true\u2019 variable, and remove the\nother overlapping sources from the \ufb01nal list. following this\ntreatment, our list of variables consisted of \u223c11, 700 sources.\n"},{"level_1":"4 Results","level_1_text":"the complete catalog of \u223c11, 700 variables is available\nat the asas-sn variable stars database (https:\/\/asas-\nsn.osu.edu\/variables) along with the v-band light curves for\neach source. table 2 lists the number of sources of each vari-\nability type in the catalog.\nin paper ii, we used the reddening-free wesenheit mag-\nnitudes (madore 1982; lebzelter et al. 2018)\nwrp = mgrp \u22121.3(gbp \u2212grp),\n(6)\nand\nwjk = mks \u22120.686(j \u2212ks)\n(7)\nfor variability classi\ufb01cation. the wesenheit wrp vs. gbp \u2212\ngrp color-magnitude diagram for all the variables is shown\nin figure 7. we have sorted the variables into groups to\nhighlight the di\ufb00erent classes of variable sources. owing to\nthe magnitude limit of asas-sn, we are only able to detect\nsu\ufb03ciently bright sources (v \u227216 mag, wrp \u22721.5 mag) in\nthe lmc. this is evident in the wesenheit color-magnitude\ndiagram for the lmc sources. for the sources outside the\nlmc, we probe a wider range of magnitudes (wrp \u22726\nmag), including rr lyrae, rotational variables and \u03b4 scuti\nvariables.\nwe have also plotted the wesenheit wrp vs. gbp \u2212\ngrp color-magnitude diagram for all the periodic variables\nin figure 8, with the points colored according to the period.\nthis essentially highlights the large dynamic range in period\nprobed by the asas-sn light curves.\nwe note that the identi\ufb01cation of mira variables in the\nlmc is hindered by blending. due to blended light, the ob-\nserved asas-sn amplitudes of these sources fall below the\namplitude threshold of v > 2 mag that is used to de\ufb01ne a\nmira variable in our pipeline. in reality, some fraction of the\nlmc semi-regular variables in this catalog are actually mira\nvariables. from the sample of known semi-regular variables\nin the lmc, we estimate that the fraction of mira variables\nclassi\ufb01ed as semi-regular variables is \u223c23%.\nusing the same color scheme, the combined wesenheit\nwjk plr diagram for the periodic variables is shown in\nfigure 9. the plr sequences for the cepheids and semi-\nregular variables in the lmc are well de\ufb01ned (soszynski\net al. 2005). most of the eclipsing binaries identi\ufb01ed in the\nlmc are either detached or semi-detached systems, and do\nnot follow the well de\ufb01ned plr for contact binaries that\nis observed in the plr diagram for the sources outside the\nlmc.\nwe also show the sky distribution of the variables iden-\nti\ufb01ed in this work in figure 10. we see that the distribution\nof eclipsing binaries and rotational variables (black points)\nis random, but the distribution of cepheids is strongly clus-\ntered towards the lmc as is expected. we also note the\nclustering of semi-regular\/irregular variables (red giants) to-\nwards the lmc and the galactic disk.\nwe matched our list of variables to the vsx (watson et\nal. 2006) catalog available in october 2018, with a matching\nradius of 16.\n\u2032\u20320 to identify previously discovered variables.\nmnras 000, 1\u201313 (2018)\nasas-sn catalog of variable stars iii\n7\ntable 2. variables by type\nvsx type\ndescription\nlmc\nnot lmc\nnew discoveries\ncwa\nw virginis type variables with p > 8 d\n10\n\u2013\n1\ncwb\nw virginis type variables with p < 8 d\n4\n8\n2\ndcep\nfundamental mode classical cepheids\n577\n12\n12\ndceps\nfirst overtone cepheids\n280\n9\n10\ndsct\n\u03b4 scuti variables\n\u2013\n44\n42\nea\ndetached algol-type binaries\n103\n1109\n865\neb\n\u03b2 lyrae-type binaries\n129\n523\n353\new\nw ursae majoris type binaries\n97\n1961\n1228\nell\nellipsoidal variables\n1\n11\n12\nhads\nhigh amplitude \u03b4 scuti variables\n\u2013\n102\n61\nrot\nrotational variables\n\u2013\n881\n813\nrrab\nrr lyrae variables (type ab)\n42\n444\n44\nrrc\nfirst overtone rr lyrae variables\n4\n443\n217\nrrd\ndouble mode rr lyrae variables\n\u2013\n4\n3\nrva\nrv tauri variables (subtype a)\n9\n1\n1\nsr\nsemi-regular variables\n1017\n1487\n1340\nl\nirregular variables\n298\n137\n262\ngcas\n\u03b3 cassiopeiae variables\n191\n49\n128\nyso\nyoung stellar objects\n2\n8\n6\nrot:\nuncertain rotational variables\n\u2013\n186\n174\ndsct:\nuncertain \u03b4 scuti variables\n4\n63\n48\ngcas:\nuncertain \u03b3 cassiopeiae variables\n10\n\u2013\n3\nvar\ngeneric variables\n40\n1390\n1385\n1\n0\n1\n2\n3\n4\n5\n6\ngbp \u2212grp\n10.0\n7.5\n5.0\n2.5\n0.0\n2.5\n5.0\nwrp\nnot lmc\n\u03b3 cassiopeiae stars\ncepheids\ndelta scuti\neclipsing binaries\nrr lyrae\nrotational variables\nsemi-regular\/irregular variables\n1\n0\n1\n2\n3\n4\n5\n6\ngbp \u2212grp\n14\n12\n10\n8\n6\n4\n2\n0\n2\nwrp\nlmc\nfigure 7. the wesenheit wrp vs. gbp \u2212grp color-magnitude diagram for the variables, outside the lmc (left), and in the lmc\n(right).\nmnras 000, 1\u201313 (2018)\n8\nt. jayasinghe et al.\n1\n0\n1\n2\n3\n4\n5\n6\ngbp \u2212grp\n10.0\n7.5\n5.0\n2.5\n0.0\n2.5\n5.0\nwrp\nnot lmc\n0\n2\n4\n6\ngbp \u2212grp\n14\n12\n10\n8\n6\n4\n2\n0\n2\nwrp\nlmc\n0.5\n0.0\n0.5\n1.0\n1.5\n2.0\n2.5\nlog(period)\nfigure 8. the wesenheit wrp vs. gbp \u2212grp color-magnitude diagram for the periodic variables, outside the lmc (left), and in the\nlmc (right). the points are colored by the period.\nthe variables discovered by the all-sky automated survey\n(asas; pojmanski 2002) and the catalina real-time tran-\nsient survey (crts; drake et al. 2014) are included in the\nvsx database. we also match our variables to the cata-\nlogs of variable stars discovered by asas-sn (jayasinghe et\nal. 2018a), the catalogs of variable stars in the magellanic\nclouds and the galactic bulge from the optical gravita-\ntional lensing experiment (ogle; udalski 2003; pawlak\net al. 2016; soszy\u00b4\nnski et al. 2016, and references therein),\nthe gaia dr2 catalog of variables (gaia collaboration et\nal. 2018a; holl et al. 2018; gaia collaboration et al. 2018b),\nthe catalog of variables from the asteroid terrestrial-impact\nlast alert system (atlas; tonry et al. 2018; heinze et al.\n2018), the catalog of kelt variables (oelkers et al. 2018)\nand the variables from macho (alcock et al. 1997). of the\n\u223c11, 700 variables identi\ufb01ed in this work, \u223c4, 700 were pre-\nviously discovered by other surveys, as also listed in table\n2. the majority of these known variables consist of eclips-\ning binaries (\u223c31%), irregular\/semi-regular variables (\u223c28%)\nand cepheids (\u223c19%).\nthis leaves \u223c7, 000 new variables. most of the new dis-\ncoveries are eclipsing binaries (\u223c35%) and irregular\/semi-\nregular variables (\u223c23%). we also discovered 128 new gcas\nvariables, 81 of which are located in the lmc. gcas vari-\nables are rapidly rotating, early-type irregular variable stars\n(typically be stars) with mass out\ufb02ow from their equatorial\nregions. example light curves for the newly identi\ufb01ed gcas\nvariables are shown in figure 12.\nwe also discovered another long period detached eclips-\ning binary (asassn-v j080709.46\u2212591028.3) in this work.\nasassn-v j080709.46\u2212591028.3 is located away from the\nlmc and has an orbital period of porb\u223c682 d (\u223c1.9 yr). its\nlight curve shows evidence of both a primary and secondary\neclipse with a primary eclipse depth of \u223c1 mag (figure 11).\na non-negligible fraction of these new discoveries were\nclassi\ufb01ed as generic variables (\u223c20%). these are mostly low\namplitude or faint sources. example light curves are shown\nfor a subset of the newly discovered periodic (irregular) vari-\nables in figure 9 (10).\n","level_2":null,"level_2_content":null},{"level_1":"5 Conclusions","level_1_text":"we\nsystematically\nsearched\nfor\nvariable\nsources\nin\na\n\u223c1000 deg2 region surrounding the southern ecliptic pole.\nthis region is coincident with the southern continuous view-\ning zone for the tess satellite and thus, a large majority of\nthese sources will have excellent tess light curves.\nthrough our search, we identi\ufb01ed \u223c11, 700 variable\nsources, of which \u223c7, 000 are new discoveries. variable\nsources identi\ufb01ed in the lmc largely consist of luminous\nvariables, including cepheids, gcas variables (be stars)\nand red giants. we identify a broader sample of variables\noutside the lmc, including rr lyrae, eclipsing binaries,\nrotational variables and \u03b4 scuti variables.\nwe have developed a user friendly interface to re-\ntrieve pre-computed asas-sn v-band light curves for\napass sources. the v-band light curves of all the \u223c1.3m\nmnras 000, 1\u201313 (2018)\nasas-sn catalog of variable stars iii\n9\n1\n0\n1\n2\n3\nlog10(p\/days)\n10\n8\n6\n4\n2\n0\n2\n4\nwjk\nnot lmc\ncepheids\ndelta scuti\neclipsing binaries\nrr lyrae\nrotational variables\nsemi-regular variables\n1\n0\n1\n2\n3\nlog10(p\/days)\n14\n12\n10\n8\n6\n4\n2\nwjk\nlmc\nfigure 9. the wesenheit wj k plr diagram for the periodic variables, outside the lmc (left), and in the lmc (right). the points are\ncolored as in figure 7.\nsources studied in this work are available online at the\nasas-sn photometry database (https:\/\/asas-sn.osu.\nedu\/photometry). to highlight the possible blended sources,\na \ufb02ag is assigned to each source if the distance to the nearest\napass neighbor is <16.\n\u2032\u20320. the new variable sources have\nalso been added to the asas-sn variable stars database\n(https:\/\/asas-sn.osu.edu\/variables).\nas part of our ongoing e\ufb00ort to systematically analyze\nall the \u223c50 million v < 17 mag apass sources for variabil-\nity, we will gradually update this database with the light\ncurves for the sources across the remainder of the sky over\nthe course of 2019. this work provides long baseline v-band\nlight curves for a large fraction of the sources in the tess\nsouthern cvz and is a useful supplement to the short base-\nline tess light curves that possess better photometric pre-\ncision.\nacknowledgements\nwe thank the las cumbres observatory and its sta\ufb00for\nits continuing support of the asas-sn project. we also\nthank the ohio state university college of arts and sciences\ntechnology services for helping us set up and maintain the\nasas-sn variable stars and photometry databases.\nasas-sn is supported by the gordon and betty moore\nfoundation through grant gbmf5490 to the ohio state\nuniversity and nsf grant ast-1515927. development of\nasas-sn has been supported by nsf grant ast-0908816,\nthe mt. cuba astronomical foundation, the center for cos-\nmology and astroparticle physics at the ohio state univer-\nsity, the chinese academy of sciences south america cen-\nter for astronomy (cas- saca), the villum foundation,\nand george skestos.\nthis work is supported in part by scialog scholar grant\n24215 from the research corporation. tat acknowledges\nsupport from a simons foundation fellowship and from an\nibm einstein fellowship from the institute for advanced\nstudy, princeton. support for jlp is provided in part by\nthe ministry of economy, development, and tourism\u2019s mil-\nlennium science initiative through grant ic120009, awarded\nto the millennium institute of astrophysics, mas. sd ac-\nknowledges project 11573003 supported by nsfc. support\nfor mp and op has been provided by the primus\/sci\/17\naward from charles university. this work was partly sup-\nported by nsfc 11721303.\nthis work has made use of data from the european\nspace agency (esa) mission gaia (https:\/\/www.cosmos.\nesa.int\/gaia), processed by the gaia data processing and\nanalysis consortium. this publication makes use of data\nproducts from the two micron all sky survey, as well as\ndata products from the wide-\ufb01eld infrared survey explorer.\nthis research was also made possible through the use of the\naavso photometric all-sky survey (apass), funded by\nthe robert martin ayers sciences fund.\nthis research has made use of the vizier catalogue\naccess tool, cds, strasbourg, france. this research made\nmnras 000, 1\u201313 (2018)\n10\nt. jayasinghe et al.\n1h\n2h\n3h\n4h\n8h\n9h\n10h\n11h\nraj2000\n5h\n6h\n7h\n65\n60\n55\n50\n45\ndej2000\n1h\n2h\n3h\n4h\n1h\n2h\n3h\n4h\n8h\n9h\n10h\n11h\nraj2000\n5h\n6h\n7h\n65\n60\n55\n50\n45\ndej2000\n1h\n2h\n3h\n4h\n\u03b3 cassiopeiae stars\ncepheids\ndelta scuti\neclipsing binaries\nother variables\nrr lyrae\nrotational variables\nsemi-regular\/irregular variables\nfigure 10. the sky distribution of the variables in equatorial coordinates. the points are colored as in figure 7.\nualso se of astropy, a community-developed core python\npackage for astronomy (astropy collaboration, 2013).\nreferences\nalard, c. 2000, a&as, 144, 363\nalard, c., & lupton, r. h. 1998, apj, 503, 325\nalcock, c., allsman, r. a., alves, d., et al. 1997, apj, 486, 697\nastropy collaboration, robitaille, t. p., tollerud, e. j., et al.\n2013, a&a, 558, a33\nbailer-jones, c. a. l., rybizki, j., fouesneau, m., mantelet, g.,\n& andrae, r. 2018, aj, 156, 58\nbeaton, r. l., bono, g., braga, v. f., et al. 2018, space sci.\nrev., 214, 113\nbhatti, w., bouma, l. g., wallace, j., et al. 2018, astrobase,\nv0.3.8, zenodo, http:\/\/doi.org\/10.5281\/zenodo.1185231\nbrown, t. m., baliber, n., bianco, f. b., et al. 2013, pasp, 125,\n1031\nbrown, j. s., stanek, k. z., holoien, t. w.-s., et al. 2018,\narxiv:1810.00011\nclarke, d. 2002, a&a, 386, 763\ncutri, r. m., & et al. 2013, vizier online data catalog, 2328,\nderue, f., marquette, j.-b., lupone, s., et al. 2002, a&a, 389,\n149\ndrake, a. j., graham, m. j., djorgovski, s. g., et al. 2014, apjs,\n213, 9\nmnras 000, 1\u201313 (2018)\nasas-sn catalog of variable stars iii\n11\n14.53\n14.79\nasassn-v j070857.55-551605.5\nhads\np= 0.04987d\n12.49\n12.67\nasassn-v j072747.61-730926.5\new\np= 0.274d\n14.87\n15.21\nasassn-v j041658.78-731136.6\new\np= 0.3435d\n13.41\n13.91\nasassn-v j062601.93-554111.4\nea\np= 1.71d\n13.87\n14.40\nasassn-v j081924.27-573545.5\nea\np= 2.8d\n13.94\n15.60\nasassn-v j074911.18-574628.3\nea\np= 2.9d\n0.0\n0.5\n1.0\n1.5\n2.0\n12.59\n12.81\nasassn-v j063031.43-593851.3\nsr\np= 68d\n0.0\n0.5\n1.0\n1.5\n2.0\n13.40\n13.66\nasassn-v j061929.47-625313.8\nsr\np= 377d\n0.0\n0.5\n1.0\n1.5\n2.0\n15.43\n16.45\nasassn-v j080709.46-591028.3\nea\np= 682d\nphase\nv magnitude\nfigure 11. phased light curves for examples of the newly discovered periodic variables. the light curves are scaled by their minimum and\nmaximum v-band magnitudes. di\ufb00erent colored points correspond to data from the di\ufb00erent asas-sn cameras. the di\ufb00erent variability\ntypes are de\ufb01ned in table 2.\nfeast, m., & whitelock, p. a. 2014, setting the scene for gaia\nand lamost, 40.\ngaia collaboration, brown, a. g. a., vallenari, a., et al. 2018,\narxiv:1804.09365\ngaia\ncollaboration,\neyer,\nl.,\nrimoldini,\nl.,\net\nal.\n2018,\narxiv:1804.09382\ngaia collaboration, helmi, a., van leeuwen, f., et al. 2018, a&a,\n616, a12.\nheinze,\na.\nn.,\ntonry,\nj.\nl.,\ndenneau,\nl.,\net\nal.\n2018,\narxiv:1804.02132\nhenden, a. a., levine, s., terrell, d., & welch, d. l. 2015,\namerican astronomical society meeting abstracts #225, 225,\n336.16\nholl,\nb.,\naudard,\nm.,\nnienartowicz,\nk.,\net\nal.\n2018,\narxiv:1804.09373\nholtzman, j. a., shetrone, m., johnson, j. a., et al. 2015, aj,\n150, 148\nholoien, t. w.-s., prieto, j. l., bersier, d., et al. 2014, mnras,\n445, 3263\nholoien, t. w.-s., kochanek, c. s., prieto, j. l., et al. 2016,\nmnras, 455, 2918\nholoien, t. w.-s., brown, j. s., stanek, k. z., et al. 2017, mn-\nras, 471, 4966\nholoien, t. w.-s., brown, j. s., vallely, p. j., et al. 2018,\narxiv:1811.08904\nholoien, t. w.-s., huber, m. e., shappee, b. j., et al. 2018,\narxiv:1808.02890\njayasinghe, t., kochanek, c. s., stanek, k. z., et al. 2018, mn-\nras, 477, 3145\njayasinghe, t., stanek, k. z., kochanek, c. s., et al. 2018,\narxiv:1809.07329\njayasinghe, t., stanek, k. z., kochanek, c. s., et al. 2018, re-\nsearch notes of the american astronomical society, 2, 181\njayasinghe, t., stanek, k. z., kochanek, c. s., et al. 2018, re-\nsearch notes of the american astronomical society, 2, 125\nkim, d.-w., & bailer-jones, c. a. l. 2016, a&a, 587, a18\nkochanek, c. s., shappee, b. j., stanek, k. z., et al. 2017, pasp,\n129, 104502\nkov\u00b4\nacs, g., zucker, s., & mazeh, t. 2002, a&a, 391, 369\nla\ufb02er, j., & kinman, t. d. 1965, apjs, 11, 216\nmnras 000, 1\u201313 (2018)\n12\nt. jayasinghe et al.\n6500\n7000\n7500\n8000\n8500\n13.54\n14.60\nasassn-v j071629.50-645600.5\nl\n7400\n7600\n7800\n8000\n8200\n8400\n14.26\n14.64\nasassn-v j075313.82-550401.4\nl\n6500\n7000\n7500\n8000\n8500\n11.49\n11.64\nasassn-v j050831.11-785758.0\nl\n6500\n7000\n7500\n8000\n8500\n11.30\n11.58\nasassn-v j070425.61-602931.0\nl\n6500\n6750\n7000\n7250\n7500\n7750\n8000\n8250\n8500\n12.74\n13.02\nasassn-v j041637.68-591916.3\ngcas\n6500\n6750\n7000\n7250\n7500\n7750\n8000\n8250\n8500\n14.38\n14.62\nasassn-v j042015.01-582548.8\ngcas\n6500\n7000\n7500\n8000\n8500\n11.54\n11.78\nasassn-v j080339.18-585905.4\ngcas\n6500\n7000\n7500\n8000\n8500\n12.24\n12.40\nasassn-v j063718.02-712255.0\ngcas\n6500\n7000\n7500\n8000\n8500\n10.91\n11.69\nasassn-v j092300.61-675316.5\ngcas\nhjd-2450000\nv magnitude\nfigure 12. light curves for examples of the newly discovered irregular variables. the format is the same as for fig. 11\nlebzelter,\nt.,\nmowlavi,\nn.,\nmarigo,\np.,\net\nal.\n2018,\narxiv:1808.03659\nleavitt, h. s. 1908, annals of harvard college observatory, 60,\n87\nmadore, b. f. 1982, apj, 253, 575\nmarrese, p. m., marinoni, s., fabrizio, m., & altavilla, g. 2018,\narxiv:1808.09151\nmatsunaga, n. 2018, rediscovering our galaxy, 57.\nmatsunaga, n., fukushi, h., nakada, y., et al. 2006, mnras,\n370, 1979\noelkers, r. j., rodriguez, j. e., stassun, k. g., et al. 2018, aj,\n155, 39\npawlak, m., soszy\u00b4\nnski, i., udalski, a., et al. 2016, acta astron.,\n66, 421\npietrzy\u00b4\nnski, g., graczyk, d., gieren, w., et al. 2013, nature, 495,\n76\npojmanski, g. 2002, acta astron., 52, 397\nricker, g. r., winn, j. n., vanderspek, r., et al. 2015, jour-\nnal of astronomical telescopes, instruments, and systems, 1,\n014003\nrodr\u00b4\n\u0131guez, r., schmidt, s. j., jayasinghe, t., et al. 2018, re-\nsearch notes of the american astronomical society, 2, 8\nscargle, j. d. 1982, apj, 263, 835\nschmidt, s. j., shappee, b. j., van saders, j. l., et al. 2018,\narxiv:1809.04510\nschwarzenberg-czerny, a. 1996, apj, 460, l107\nshappee, b. j., prieto, j. l., grupe, d., et al. 2014, apj, 788, 48\nshields, j. v., jayasinghe, t., stanek, k. z., et al. 2018,\narxiv:1809.04075\nskrutskie, m. f., cutri, r. m., stiening, r., et al. 2006, aj, 131,\n1163\nsoszynski, i., udalski, a., kubiak, m., et al. 2005, acta astron.,\n55, 331.\nsoszy\u00b4\nnski, i., pawlak, m., pietrukowicz, p., et al. 2016, acta as-\ntron., 66, 405\nstassun, k. g., oelkers, r. j., pepper, j., et al. 2018, aj, 156,\n102\nstetson, p. b. 1996, pasp, 108, 851\ntaylor, m. b. 2005, astronomical data analysis software and\nsystems xiv, 347, 29\nthompson, t. a., kochanek, c. s., stanek, k. z., et al. 2018,\narxiv:1806.02751\ntonry, j. l., denneau, l., heinze, a. n., et al. 2018, pasp, 130,\n064505\nmnras 000, 1\u201313 (2018)\nasas-sn catalog of variable stars iii\n13\ntorres, g., andersen, j., & gim\u00b4\nenez, a. 2010, a&arv, 18, 67\ntucker, m. a., shappee, b. j., holoien, t. w.-s., et al. 2018,\narxiv:1808.07875\nudalski, a. 2003, acta astron., 53, 291\nwatson, c. l., henden, a. a., & price, a. 2006, society for as-\ntronomical sciences annual symposium, 25, 47\nwright, e. l., eisenhardt, p. r. m., mainzer, a. k., et al. 2010,\naj, 140, 1868\nwo\u00b4\nzniak, p. r., vestrand, w. t., akerlof, c. w., et al. 2004, aj,\n127, 2436\nzechmeister, m., & k\u00a8\nurster, m. 2009, a&a, 496, 577\nthis paper has been typeset from a t\nex\/l\na\nt\nex \ufb01le prepared by\nthe author.\nmnras 000, 1\u201313 (2018)\n","level_2":null,"level_2_content":null}]}